{
    "title": "Understanding Quantum Computing and Its Potential",
    "description": "Explore the basics of quantum computing, how it works, and the groundbreaking potential it holds for industries and the future of technology.",
    "content": "<h1>Understanding Quantum Computing and Its Potential</h1>\n\n<p>Quantum computing is one of the most revolutionary advancements in technology today. Unlike classical computers that use bits (0s and 1s) to process information, quantum computers use <em>qubits</em>, which can represent multiple states simultaneously. This opens up new possibilities for solving complex problems.</p>\n\n<h2>How Does Quantum Computing Work?</h2>\n\n<p>At the core of quantum computing are two principles:</p>\n\n<ul>\n  <li><strong>Superposition:</strong> Qubits can exist in multiple states at once, unlike classical bits which are either 0 or 1.</li>\n  <li><strong>Entanglement:</strong> Qubits can be interconnected in such a way that the state of one affects the state of another, no matter how far apart they are.</li>\n</ul>\n\n<p>These properties allow quantum computers to perform multiple calculations simultaneously, providing exponential speed-up for specific types of problems.</p>\n\n<h2>Applications of Quantum Computing</h2>\n\n<p>Quantum computing has the potential to transform various industries. Some of its key applications include:</p>\n\n<ul>\n  <li><strong>Drug Discovery:</strong> Simulating molecules and chemical reactions at the quantum level to accelerate drug development.</li>\n  <li><strong>Cryptography:</strong> Breaking and creating highly secure encryption methods.</li>\n  <li><strong>Optimization:</strong> Solving complex logistical and supply chain problems more efficiently.</li>\n  <li><strong>AI and Machine Learning:</strong> Enhancing the training of machine learning models with greater speed and accuracy.</li>\n</ul>\n\n<h2>Challenges in Quantum Computing</h2>\n\n<p>Despite its promise, quantum computing faces significant challenges:</p>\n\n<ul>\n  <li><strong>Stability:</strong> Qubits are highly sensitive to environmental factors, requiring extreme conditions to maintain stability.</li>\n  <li><strong>Scalability:</strong> Building large-scale quantum computers with enough qubits is still a major hurdle.</li>\n  <li><strong>Cost:</strong> The technology is incredibly expensive, limiting access to a few organizations and research institutions.</li>\n</ul>\n\n<h2>The Future of Quantum Computing</h2>\n\n<p>While still in its infancy, quantum computing holds immense potential for the future:</p>\n\n<ul>\n  <li>Collaborations between tech giants and research institutions are driving rapid progress.</li>\n  <li>Advances in quantum hardware and software will make this technology more accessible over time.</li>\n  <li>Quantum computing may enable solutions to problems previously thought unsolvable.</li>\n</ul>\n\n<h2>Conclusion</h2>\n\n<p>Quantum computing represents a paradigm shift in how we approach computation. Though there are challenges to overcome, its potential to revolutionize industries and solve complex problems is undeniable. As the technology matures, its impact will be felt across the globe.</p>",
    "image": "thumbnails/quatum-computing-1.jpg",
    "category": "Technology",
    "slug": "understanding-quantum-computing"
  }
  